pydantic_state/__init__.py
pydantic_state/base_redis_state_model.py
pydantic_state/config.py
pydantic_state/redis_client.py
pydantic_state-0.0.7.dist-info/licenses/LICENCE
pydantic_state-0.0.7.dist-info/METADATA
pydantic_state-0.0.7.dist-info/WHEEL
pydantic_state-0.0.7.dist-info/top_level.txt
pydantic_state-0.0.7.dist-info/RECORD
